tecex_tools/__init__.py
tecex_tools/cli.py
tecex_tools/helpers.py
tecex_tools/models.py
tecex_tools-0.1.5.dist-info/entry_points.txt
tecex_tools-0.1.5.dist-info/WHEEL
tecex_tools-0.1.5.dist-info/METADATA
tecex_tools-0.1.5.dist-info/RECORD
