Metadata-Version: 2.1
Name: tecex-tools
Version: 0.1.5
Summary: A CLI application for Texec containing a customised set of tools
Author: Scott Fuller
Author-email: fullerscott085@gmail.com
Requires-Python: >=3.8,<4.0
Classifier: Programming Language :: Python :: 3
Classifier: Programming Language :: Python :: 3.8
Classifier: Programming Language :: Python :: 3.9
Classifier: Programming Language :: Python :: 3.10
Classifier: Programming Language :: Python :: 3.11
Requires-Dist: openpyxl (>=3.0.10,<4.0.0)
Requires-Dist: pandas (>=1.5.1,<2.0.0)
Requires-Dist: pytest (>=7.2.0,<8.0.0)
Requires-Dist: typer[all] (>=0.7.0,<0.8.0)
